{
  "type": "FeatureCollection",
  "features": [
    {
      "type": "Feature",
      "properties": { "title": "Punta Sur Eco Beach Park" },
      "geometry": { "type": "Point", "coordinates": [-86.977, 20.346] }
    },
    {
      "type": "Feature",
      "properties": { "title": "Faro Celarain (El Faro) Lighthouse" },
      "geometry": { "type": "Point", "coordinates": [-86.977, 20.346] }
    },
    {
      "type": "Feature",
      "properties": { "title": "San Gervasio Ruins" },
      "geometry": { "type": "Point", "coordinates": [-86.857, 20.327] }
    },
    {
      "type": "Feature",
      "properties": { "title": "Cozumel Jungle Tours" },
      "geometry": { "type": "Point", "coordinates": [-86.857, 20.327] }
    },
    {
      "type": "Feature",
      "properties": { "title": "Blvd. Rafael E. Melgar Scenic Drive" },
      "geometry": { "type": "Point", "coordinates": [-86.946, 20.510] }
    },
    {
      "type": "Feature",
      "properties": { "title": "El Cedral (Traditional Mayan Village)" },
      "geometry": { "type": "Point", "coordinates": [-86.931, 20.342] }
    },
    {
      "type": "Feature",
      "properties": { "title": "Road to El Caracol (The Snail)" },
      "geometry": { "type": "Point", "coordinates": [-86.977, 20.346] }
    },
    {
      "type": "Feature",
      "properties": { "title": "Cozumel Island Beaches & Off-Road Adventures" },
      "geometry": { "type": "Point", "coordinates": [-86.946, 20.510] }
    },
    {
      "type": "Feature",
      "properties": { "title": "El Caracol Ecological Reserve" },
      "geometry": { "type": "Point", "coordinates": [-86.977, 20.346] }
    }
  ]
}
